SPEAK/__init__.py
SPEAK/speak.py
textspeech-0.0.1.dist-info/LICENSE.txt
textspeech-0.0.1.dist-info/METADATA
textspeech-0.0.1.dist-info/WHEEL
textspeech-0.0.1.dist-info/top_level.txt
textspeech-0.0.1.dist-info/RECORD
